hope_os/__init__.py
hope_os/hope_os.cpython-39-darwin.so
hope_os/py.typed
hope_os-0.2.0.dist-info/METADATA
hope_os-0.2.0.dist-info/WHEEL
hope_os-0.2.0.dist-info/licenses/LICENSE
hope_os-0.2.0.dist-info/RECORD
