Metadata-Version: 2.4
Name: hope-os
Version: 0.2.0
Classifier: Development Status :: 4 - Beta
Classifier: Intended Audience :: Developers
Classifier: Intended Audience :: Science/Research
Classifier: License :: OSI Approved :: MIT License
Classifier: Operating System :: OS Independent
Classifier: Programming Language :: Python :: 3
Classifier: Programming Language :: Python :: 3.8
Classifier: Programming Language :: Python :: 3.9
Classifier: Programming Language :: Python :: 3.10
Classifier: Programming Language :: Python :: 3.11
Classifier: Programming Language :: Python :: 3.12
Classifier: Programming Language :: Rust
Classifier: Topic :: Scientific/Engineering :: Artificial Intelligence
Classifier: Topic :: Software Development :: Libraries :: Python Modules
Requires-Dist: pytest>=7.0 ; extra == 'dev'
Requires-Dist: pytest-asyncio>=0.21 ; extra == 'dev'
Requires-Dist: mypy>=1.0 ; extra == 'dev'
Requires-Dist: ruff>=0.1 ; extra == 'dev'
Provides-Extra: dev
License-File: LICENSE
Summary: Multimodal cognitive kernel - 23 modules, vision, persistent memory, dream consolidation, 0.36ms latency
Keywords: ai,cognitive,self-aware,neural,memory
Home-Page: https://github.com/silentnoisehun/Hope-Os
Author-email: Máté Róbert <mate@hope-os.dev>
Requires-Python: >=3.8
Project-URL: Changelog, https://github.com/silentnoisehun/Hope-Os/blob/main/CHANGELOG.md
Project-URL: Documentation, https://docs.rs/hope-os
Project-URL: Homepage, https://github.com/silentnoisehun/Hope-Os
Project-URL: Repository, https://github.com/silentnoisehun/Hope-Os
